delb_reference_plugins/__init__.py
delb_reference_plugins/custom_loader.py
delb_reference_plugins/tei_header_properties.py
delb_reference_plugins-0.4.dist-info/METADATA
delb_reference_plugins-0.4.dist-info/WHEEL
delb_reference_plugins-0.4.dist-info/entry_points.txt
delb_reference_plugins-0.4.dist-info/top_level.txt
delb_reference_plugins-0.4.dist-info/RECORD
